sparkwise/__init__.py
sparkwise/cli.py
sparkwise/config_qa.py
sparkwise/core/__init__.py
sparkwise/core/advanced_skew_detector.py
sparkwise/core/advisor.py
sparkwise/core/delta_check.py
sparkwise/core/native_check.py
sparkwise/core/pool_check.py
sparkwise/core/query_plan_analyzer.py
sparkwise/core/runtime_check.py
sparkwise/core/skew_check.py
sparkwise/knowledge_base/delta_configs.yaml
sparkwise/knowledge_base/fabric_configs.yaml
sparkwise/knowledge_base/fabric_runtime_1.2_configs.yaml
sparkwise/knowledge_base/spark_configs.yaml
sparkwise/profiling/__init__.py
sparkwise/profiling/efficiency_analyzer.py
sparkwise/profiling/executor_profiler.py
sparkwise/profiling/job_profiler.py
sparkwise/profiling/resource_profiler.py
sparkwise/profiling/scalability_predictor.py
sparkwise/profiling/session_profiler.py
sparkwise/profiling/stage_timeline.py
sparkwise/profiling/storage_optimizer.py
sparkwise-1.4.2.dist-info/licenses/LICENSE
sparkwise-1.4.2.dist-info/METADATA
sparkwise-1.4.2.dist-info/WHEEL
sparkwise-1.4.2.dist-info/entry_points.txt
sparkwise-1.4.2.dist-info/top_level.txt
sparkwise-1.4.2.dist-info/RECORD
