Metadata-Version: 2.4
Name: sparkwise
Version: 1.4.2
Summary: Automated Data Engineering specialist for Fabric Spark workloads - intelligent configuration analysis and optimization recommendations
Author-email: Santhosh Ravindran <santhoshravindran7@users.noreply.github.com>
License: MIT
Project-URL: Homepage, https://github.com/santhoshravindran7/sparkwise
Project-URL: Repository, https://github.com/santhoshravindran7/sparkwise
Project-URL: Issues, https://github.com/santhoshravindran7/sparkwise/issues
Keywords: spark,fabric,microsoft-fabric,optimization,pyspark,delta,configuration
Classifier: Development Status :: 3 - Alpha
Classifier: Intended Audience :: Developers
Classifier: Topic :: Software Development :: Libraries :: Python Modules
Classifier: License :: OSI Approved :: MIT License
Classifier: Programming Language :: Python :: 3
Classifier: Programming Language :: Python :: 3.8
Classifier: Programming Language :: Python :: 3.9
Classifier: Programming Language :: Python :: 3.10
Classifier: Programming Language :: Python :: 3.11
Classifier: Programming Language :: Python :: 3.12
Requires-Python: >=3.8
License-File: LICENSE
Requires-Dist: pyspark>=3.3.0
Requires-Dist: rich>=10.0.0
Requires-Dist: pyyaml>=6.0
Requires-Dist: typing-extensions>=4.0.0
Provides-Extra: dev
Requires-Dist: pytest>=7.0.0; extra == "dev"
Requires-Dist: pytest-cov>=4.0.0; extra == "dev"
Requires-Dist: black>=23.0.0; extra == "dev"
Requires-Dist: mypy>=1.0.0; extra == "dev"
Requires-Dist: ruff>=0.1.0; extra == "dev"
Dynamic: license-file
